pybluebolt_service/__init__.py
pybluebolt_service/const.py
pybluebolt_service-0.0.2.dist-info/LICENSE.md
pybluebolt_service-0.0.2.dist-info/METADATA
pybluebolt_service-0.0.2.dist-info/WHEEL
pybluebolt_service-0.0.2.dist-info/top_level.txt
pybluebolt_service-0.0.2.dist-info/zip-safe
pybluebolt_service-0.0.2.dist-info/RECORD
