Metadata-Version: 2.1
Name: pybluebolt-service
Version: 0.0.2
Summary: Python interface for BlueBOLT cloud service
Home-page: https://github.com/rsnodgrass/pybluebolt-service
Author: Ryan Snodgrass
Author-email: rsnodgrass@gmail.com
License: Apache Software License
Keywords: bluebolt,home automation,panamax,furman
Platform: UNKNOWN
Classifier: Programming Language :: Python :: 3
Classifier: License :: OSI Approved :: Apache Software License
Classifier: Operating System :: OS Independent
Requires-Dist: requests (>=2.0)
